LICENSE
MANIFEST.in
README.md
setup.py
bin/maryam
maryam/__init__.py
maryam/__main__.py
maryam.egg-info/PKG-INFO
maryam.egg-info/SOURCES.txt
maryam.egg-info/dependency_links.txt
maryam.egg-info/requires.txt
maryam.egg-info/top_level.txt
maryam/core/__init__.py
maryam/core/basedir.py
maryam/core/core.py
maryam/core/initial.py
maryam/core/util/__init__.py
maryam/core/util/engines/__init__.py
maryam/core/util/engines/baidu.py
maryam/core/util/engines/bing.py
maryam/core/util/engines/bing_images.py
maryam/core/util/engines/duckduckgo.py
maryam/core/util/engines/etools.py
maryam/core/util/engines/google.py
maryam/core/util/engines/google_images.py
maryam/core/util/engines/startpage.py
maryam/core/util/engines/yahoo.py
maryam/core/util/engines/yandex.py
maryam/core/util/footprint/__init__.py
maryam/core/util/helpers/__init__.py
maryam/core/util/helpers/keywords.py
maryam/core/util/helpers/page_parse.py
maryam/core/util/helpers/rand_uagent.py
maryam/core/util/helpers/reglib.py
maryam/core/util/helpers/urlib.py
maryam/core/util/helpers/web_scrap.py
maryam/core/util/iris/__init__.py
maryam/core/util/iris/chart.py
maryam/core/util/iris/cluster.py
maryam/core/util/iris/meta_search_util.py
maryam/core/util/iris/retriever.py
maryam/core/util/iris/safe_searcher.py
maryam/core/util/iris/tf_histogram.py
maryam/core/util/iris/topic.py
maryam/core/util/iris/word_cloud.py
maryam/core/util/osint/__init__.py
maryam/core/util/osint/ahmia.py
maryam/core/util/osint/bing_mobile_view.py
maryam/core/util/osint/darksearch.py
maryam/core/util/osint/exalead.py
maryam/core/util/osint/hunter.py
maryam/core/util/osint/keyserver.py
maryam/core/util/osint/netcraft.py
maryam/core/util/osint/numverify.py
maryam/core/util/osint/onionland.py
maryam/core/util/osint/reddit.py
maryam/core/util/osint/tweet_search.py
maryam/core/util/osint/urlscan.py
maryam/core/util/osint/virustotal.py
maryam/core/util/search/__init__.py
maryam/core/util/search/arxiv.py
maryam/core/util/search/ask.py
maryam/core/util/search/crt.py
maryam/core/util/search/dictionary.py
maryam/core/util/search/discord.py
maryam/core/util/search/instagram.py
