Metadata-Version: 2.1
Name: maryam
Version: 2.5.3.post1
Summary: OWASP Maryam is a modular/optional open-source framework based on OSINT and data gathering.
Home-page: https://github.com/saeeddhqan/Maryam
Author: Saeed Dehqan
License: GPL-V3
Keywords: OWASP,OSINT,search-engine,social-networks,Maryam
Classifier: Programming Language :: Python :: 3.12
Classifier: Development Status :: 5 - Production/Stable
Classifier: License :: OSI Approved :: GNU General Public License v3 (GPLv3)
Classifier: Natural Language :: English
Classifier: Operating System :: POSIX :: Linux
Classifier: Environment :: Console
License-File: LICENSE
